tld_parser/__init__.py
tld_parser/errors.py
tld_parser/parser.py
tld_parser-2.0.0.dist-info/LICENSE
tld_parser-2.0.0.dist-info/WHEEL
tld_parser-2.0.0.dist-info/METADATA
tld_parser-2.0.0.dist-info/RECORD
