Metadata-Version: 2.1
Name: tld-parser
Version: 2.0.0
Summary: Parse tlds from domains.
License: MIT
Author: theelous3
Author-email: theegrandmaster@gmail.com
Requires-Python: >=3.8,<4.0
Classifier: License :: OSI Approved :: MIT License
Classifier: Programming Language :: Python :: 3
Classifier: Programming Language :: Python :: 3.8
Classifier: Programming Language :: Python :: 3.9
Requires-Dist: attrs (>=21.2.0,<22.0.0)
